officehours/__init__.py
officehours/main.py
officehours-0.1.7.dist-info/DESCRIPTION.rst
officehours-0.1.7.dist-info/METADATA
officehours-0.1.7.dist-info/RECORD
officehours-0.1.7.dist-info/WHEEL
officehours-0.1.7.dist-info/metadata.json
officehours-0.1.7.dist-info/top_level.txt
