Metadata-Version: 2.0
Name: officehours
Version: 0.1.7
Summary: Utility to calculate time intervals in working hours
Home-page: https://github.com/Funk66/officehours.git
Author: Guillermo Guirao Aguilar
Author-email: contact@guillermoguiraoaguilar.com
License: UNKNOWN
Keywords: time,hours,office,business,work
Platform: UNKNOWN
Classifier: Development Status :: 5 - Production/Stable
Classifier: Natural Language :: English
Classifier: Programming Language :: Python
Classifier: Programming Language :: Python :: 2
Classifier: Programming Language :: Python :: 2.7
Classifier: Programming Language :: Python :: 3
Classifier: Programming Language :: Python :: 3.3
Classifier: Programming Language :: Python :: 3.4
Classifier: Programming Language :: Python :: 3.5
Classifier: Programming Language :: Python :: 3.6
Classifier: Topic :: Utilities
